<?xml version="1.0" encoding="UTF-8"?>
<gresources>
    <gresource prefix="/org/chrysalide/gui/core/images">
        <file compressed="true" alias="palette.png">../../../pixmaps/palette.png</file>
        <file compressed="true" alias="collapse.png">../../../pixmaps/collapse.png</file>
        <file compressed="true" alias="collapse_dark.png">../../../pixmaps/collapse_dark.png</file>
        <file compressed="true" alias="expand.png">../../../pixmaps/expand.png</file>
        <file compressed="true" alias="expand_dark.png">../../../pixmaps/expand_dark.png</file>
        <file compressed="true" alias="snapshot.png">../../../pixmaps/snapshot.png</file>
        <file compressed="true" alias="snapshot_current.png">../../../pixmaps/snapshot_current.png</file>
    </gresource>
</gresources>
