<?xml version="1.0" encoding="UTF-8"?>
<ChrysalideTheme>
  <identity>
    <name>Solarized</name>
    <author>Cyrille Bagard</author>
    <desc>Precision colors for Chrysalide based on https://ethanschoonover.com/solarized/</desc>
  </identity>
  <resources>
    <common>
      <path>palette.css</path>
    </common>
    <light>
      <path>tokens-light.css</path>
      <path>widgets-light.css</path>
    </light>
    <dark>
      <path>tokens-dark.css</path>
      <path>widgets-dark.css</path>
    </dark>
  </resources>
</ChrysalideTheme>
